anonfiles/__init__.py
anonfiles/main.py
anonfiles-1.0.3.dist-info/LICENSE
anonfiles-1.0.3.dist-info/METADATA
anonfiles-1.0.3.dist-info/WHEEL
anonfiles-1.0.3.dist-info/entry_points.txt
anonfiles-1.0.3.dist-info/top_level.txt
anonfiles-1.0.3.dist-info/RECORD
