Metadata-Version: 2.1
Name: anonfiles
Version: 1.0.3
Summary: upload and download to anonfiless server
Home-page: https://github.com/redevil1/anonfiles
Author: Jak Bin
Author-email: jakbin4747@gmail.com
License: UNKNOWN
Project-URL: Bug Tracker, https://github.com/redevil1/anonfiless/issues
Keywords: anonfiles,anonfiles-api,anonfiles-cli,anonymous,upload
Platform: UNKNOWN
Classifier: Programming Language :: Python :: 3.6
Classifier: License :: OSI Approved :: MIT License
Classifier: Natural Language :: English
Classifier: Operating System :: OS Independent
Requires-Python: >=3
License-File: LICENSE
Requires-Dist: requests
Requires-Dist: requests-toolbelt
Requires-Dist: tqdm
